auditok/__init__.py
auditok/cmdline.py
auditok/cmdline_util.py
auditok/core.py
auditok/dataset.py
auditok/exceptions.py
auditok/io.py
auditok/plotting.py
auditok/signal.py
auditok/signal_numpy.py
auditok/util.py
auditok/workers.py
auditok/data/1to6arabic_16000_mono_bc_noise.wav
auditok/data/was_der_mensch_saet_das_wird_er_vielfach_ernten_44100Hz_mono_lead_trail_silence.wav
auditok-0.2.0.dist-info/LICENSE
auditok-0.2.0.dist-info/METADATA
auditok-0.2.0.dist-info/WHEEL
auditok-0.2.0.dist-info/entry_points.txt
auditok-0.2.0.dist-info/top_level.txt
auditok-0.2.0.dist-info/RECORD
